datefind/__init__.py
datefind/constants.py
datefind/datefind.py
datefind/py.typed
datefind/utils/__init__.py
datefind/utils/date_factory.py
datefind-0.2.1.dist-info/METADATA
datefind-0.2.1.dist-info/WHEEL
datefind-0.2.1.dist-info/licenses/LICENSE
datefind-0.2.1.dist-info/RECORD
