Metadata-Version: 2.4
Name: datefind
Version: 0.2.1
Summary: A python module for locating dates within text.
Project-URL: Homepage, https://github.com/natelandau/datefind
Project-URL: Repository, https://github.com/natelandau/datefind
Author-email: Nate Landau <github@natenate.org>
License-Expression: MIT
License-File: LICENSE
Classifier: License :: OSI Approved :: MIT License
Classifier: Programming Language :: Python :: 3.11
Classifier: Programming Language :: Python :: 3.12
Classifier: Programming Language :: Python :: 3.13
Requires-Python: <=3.13,>=3.11
Requires-Dist: regex>=2024.11.6
Requires-Dist: tzlocal>=5.3.1
